mlxformers-0.1.3.dist-info/METADATA
mlxformers-0.1.3.dist-info/WHEEL
mlxformers-0.1.3.dist-info/licenses/LICENSE
mlxformers/__init__.py
mlxformers/modeling_mlx_outputs.py
mlxformers/modeling_mlx_utils.py
mlxformers/models/__init__.py
mlxformers/models/sam/__init__.py
mlxformers/models/sam/convert_sam_to_mlxformers.py
mlxformers/models/sam/modeling_mlx_sam.py
mlxformers-0.1.3.dist-info/RECORD
